main.py
src/__init__.py
src/server.py
src/tree_generator.py
file_tools_mcp-0.1.0.dist-info/METADATA
file_tools_mcp-0.1.0.dist-info/WHEEL
file_tools_mcp-0.1.0.dist-info/entry_points.txt
file_tools_mcp-0.1.0.dist-info/licenses/LICENSE
file_tools_mcp-0.1.0.dist-info/RECORD
