Metadata-Version: 2.4
Name: file-tools-mcp
Version: 0.1.0
Summary: MCP server providing file tools for LLMs and coding agents to quickly get project context
Project-URL: Homepage, https://github.com/BumpyClock/file-tools-mcp
Project-URL: Repository, https://github.com/BumpyClock/file-tools-mcp
Project-URL: Issues, https://github.com/BumpyClock/file-tools-mcp/issues
Author-email: Your Name <your.email@example.com>
License: MIT
License-File: LICENSE
Keywords: ai,assistant,claude,file-tools,llm,mcp
Classifier: Development Status :: 4 - Beta
Classifier: Intended Audience :: Developers
Classifier: License :: OSI Approved :: MIT License
Classifier: Programming Language :: Python :: 3
Classifier: Programming Language :: Python :: 3.12
Classifier: Topic :: Software Development :: Libraries :: Python Modules
Requires-Python: >=3.12
Requires-Dist: mcp[cli]>=1.11.0
Requires-Dist: pathspec>=0.12.1
